kotlin_jupyter_kernel-0.15.0.598.data/data/share/jupyter/kernels/kotlin/kernel.css
kotlin_jupyter_kernel-0.15.0.598.data/data/share/jupyter/kernels/kotlin/kernel.js
kotlin_jupyter_kernel-0.15.0.598.data/data/share/jupyter/kernels/kotlin/kernel.json
kotlin_jupyter_kernel-0.15.0.598.data/data/share/jupyter/kernels/kotlin/logo-16x16.png
kotlin_jupyter_kernel-0.15.0.598.data/data/share/jupyter/kernels/kotlin/logo-64x64.png
kotlin_jupyter_kernel-0.15.0.598.data/data/share/jupyter/kernels/kotlin/wavyline-orange.gif
kotlin_jupyter_kernel-0.15.0.598.data/data/share/jupyter/kernels/kotlin/wavyline-red.gif
kotlin_kernel/__init__.py
kotlin_kernel/__main__.py
kotlin_kernel/add_kernel.py
kotlin_kernel/detect_jars_location.py
kotlin_kernel/env_names.py
kotlin_kernel/install_user.py
kotlin_kernel/port_generator.py
run_kotlin_kernel/__init__.py
run_kotlin_kernel/__main__.py
run_kotlin_kernel/run_kernel.py
run_kotlin_kernel/config/jar_args.json
run_kotlin_kernel/jars/annotations-13.0.jar
run_kotlin_kernel/jars/api-0.15.0-598.jar
run_kotlin_kernel/jars/kotlin-jupyter-kernel-0.15.0-598-all.jar
run_kotlin_kernel/jars/kotlin-reflect-2.2.20-Beta2.jar
run_kotlin_kernel/jars/kotlin-script-runtime-2.2.20-Beta2.jar
run_kotlin_kernel/jars/kotlin-stdlib-2.2.20-Beta2.jar
run_kotlin_kernel/jars/kotlinx-serialization-core-jvm-1.9.0.jar
run_kotlin_kernel/jars/kotlinx-serialization-json-jvm-1.9.0.jar
run_kotlin_kernel/jars/lib-0.15.0-598.jar
run_kotlin_kernel/jars/protocol-api-0.15.0-598.jar
run_kotlin_kernel/jars/slf4j-api-2.0.17.jar
run_kotlin_kernel/libraries/2p-kt.json
run_kotlin_kernel/libraries/adventOfCode.json
run_kotlin_kernel/libraries/biokotlin.json
run_kotlin_kernel/libraries/combinatoricskt.json
run_kotlin_kernel/libraries/commit_sha
run_kotlin_kernel/libraries/coroutines.json
run_kotlin_kernel/libraries/dataframe.json
run_kotlin_kernel/libraries/datetime.json
run_kotlin_kernel/libraries/deeplearning4j-cuda.json
run_kotlin_kernel/libraries/deeplearning4j.json
kotlin_jupyter_kernel-0.15.0.598.dist-info/METADATA
kotlin_jupyter_kernel-0.15.0.598.dist-info/WHEEL
kotlin_jupyter_kernel-0.15.0.598.dist-info/top_level.txt
kotlin_jupyter_kernel-0.15.0.598.dist-info/RECORD
