Metadata-Version: 2.4
Name: kotlin-jupyter-kernel
Version: 0.15.0.598
Summary: Kotlin kernel for Jupyter notebooks
Home-page: https://github.com/Kotlin/kotlin-jupyter
Author: JetBrains
License: Apache 2.0
Classifier: Framework :: Jupyter
Classifier: Development Status :: 4 - Beta
Classifier: Programming Language :: Kotlin
Classifier: License :: OSI Approved :: Apache Software License
Classifier: Intended Audience :: Science/Research
Classifier: Operating System :: OS Independent
Classifier: Topic :: Software Development :: Interpreters
Dynamic: author
Dynamic: classifier
Dynamic: description
Dynamic: description-content-type
Dynamic: home-page
Dynamic: license
Dynamic: summary
